woolf_sabbat_5/.gitignore
woolf_sabbat_5/__init__.py
woolf_sabbat_5/base_objects/__init__.py
woolf_sabbat_5/base_objects/book_object.py
woolf_sabbat_5/base_objects/commands_object.py
woolf_sabbat_5/base_objects/main_objects.py
woolf_sabbat_5/base_objects/note_object.py
woolf_sabbat_5/base_objects/record_object.py
woolf_sabbat_5/main.py
woolf_sabbat_5/requirement.txt
woolf_sabbat_5/utilities/__init__.py
woolf_sabbat_5/utilities/birtday_output.py
woolf_sabbat_5/utilities/error_handler.py
woolf_sabbat_5/utilities/help_message.py
woolf_sabbat_5/utilities/input_reader.py
woolf_sabbat_5/utilities/storage.py
woolf_sabbat_5-0.0.4.dist-info/METADATA
woolf_sabbat_5-0.0.4.dist-info/WHEEL
woolf_sabbat_5-0.0.4.dist-info/RECORD
